{
  "title": "reset_button",
  "display_title": "Reset Insurance Button",
  "content": [
    {
      "template": "image-block",
      "image": "https://s3.amazonaws.com/cms.thisispete.com/reset1_a6a9b3993b.jpg",
      "alt_text": "Giant novelty button with the word 'reset' displayed, electronics",
      "description": ""
    },
    {
      "template": "image-block",
      "image": "https://s3.amazonaws.com/cms.thisispete.com/reset4_8448b41940.jpg",
      "alt_text": "Trade show booth rendering with giant reset button",
      "description": "<p>Worked with the team at Fjord, and John Murray Productions to create this massive reset button to promote the 'Three' insurance product by Berkshire Hathaway at their annual shareholder meeting in Omaha Nebraska.</p><p>The concept was to have this oversized reset button, that had some lighting effects, and when pressed the lights would change, and it would trigger a video on the wall behind it to play.</p>"
    },
    {
      "template": "video-block",
      "vimeo_id": "332487293",
      "title": "button demo",
      "description": "<p>I whipped up an arduino controller that controlled the lighting over DMX, and connected to a computer as a USB keyboard, then coded a custom video player app in open-frameworks to handle the video playback and keyboard control.</p>"
    },
    {
      "template": "image-block",
      "description": "<p>Here's the final piece working on the tradeshow floor</p>",
      "alt_text": "Final reset button installed in trade show booth",
      "image": "https://s3.amazonaws.com/cms.thisispete.com/reset3_ba4ce7e7eb.jpg"
    },
    {
      "template": "video-block",
      "vimeo_id": "336239295",
      "title": "reset button demo video",
      "description": ""
    },
    {
      "template": "image-block",
      "description": "<p>And here's the money shot of Warren Buffet interacting with it</p>",
      "alt_text": "Warren Buffet pushing the reset button, with some help",
      "image": "https://s3.amazonaws.com/cms.thisispete.com/reset2_e54b3ee3ff.jpg"
    }
  ],
  "footer": "",
  "template": "blog"
}
